[{"code":"2ccddc1d-1a5d-47a6-8568-e6f424daf90a","createdAt":"2022/7/21 22:04:06","temperature":"29.75","humidity":"38.72","iaq":"0.00","id":"0"},{"code":"ecd81246-5f31-4556-bd68-1f8c4978f2a1","createdAt":"2022/7/22 01:18:59","temperature":"29.86","humidity":"41.44","iaq":"0.00","id":"1"},{"code":"2ccddc1d-1a5d-47a6-8568-e6f424daf90a","createdAt":"2022/7/22 01:20:41","temperature":"29.50","humidity":"41.90","iaq":"0.00","id":"2"},{"code":"03e7a84c-46da-4811-a7db-174e79e85c36","createdAt":"2022/7/22 01:21:16","temperature":"29.87","humidity":"41.52","iaq":"0.00","id":"3"},{"code":"ecd81246-5f31-4556-bd68-1f8c4978f2a1","createdAt":"2022/7/22 01:23:04","temperature":"29.86","humidity":"41.47","iaq":"0.00","id":"4"},{"code":"2ccddc1d-1a5d-47a6-8568-e6f424daf90a","createdAt":"2022/7/22 01:24:45","temperature":"29.41","humidity":"42.09","iaq":"4.34","id":"5"},{"code":"03e7a84c-46da-4811-a7db-174e79e85c36","createdAt":"2022/7/22 01:25:20","temperature":"29.84","humidity":"41.59","iaq":"0.00","id":"6"},{"code":"ecd81246-5f31-4556-bd68-1f8c4978f2a1","createdAt":"2022/7/22 01:27:10","temperature":"29.85","humidity":"41.52","iaq":"0.00","id":"7"},{"code":"2ccddc1d-1a5d-47a6-8568-e6f424daf90a","createdAt":"2022/7/22 01:28:51","temperature":"29.40","humidity":"42.16","iaq":"4.49","id":"8"},{"code":"03e7a84c-46da-4811-a7db-174e79e85c36","createdAt":"2022/7/22 01:29:24","temperature":"29.81","humidity":"41.65","iaq":"0.00","id":"9"},{"code":"ecd81246-5f31-4556-bd68-1f8c4978f2a1","createdAt":"2022/7/22 01:31:15","temperature":"29.83","humidity":"41.54","iaq":"0.00","id":"10"},{"code":"2ccddc1d-1a5d-47a6-8568-e6f424daf90a","createdAt":"2022/7/22 01:32:56","temperature":"29.38","humidity":"42.23","iaq":"4.64","id":"11"},{"code":"03e7a84c-46da-4811-a7db-174e79e85c36","createdAt":"2022/7/22 01:33:29","temperature":"29.79","humidity":"41.70","iaq":"0.00","id":"12"},{"code":"ecd81246-5f31-4556-bd68-1f8c4978f2a1","createdAt":"2022/7/22 01:35:19","temperature":"29.82","humidity":"41.56","iaq":"0.00","id":"13"},{"code":"2ccddc1d-1a5d-47a6-8568-e6f424daf90a","createdAt":"2022/7/22 01:37:01","temperature":"29.35","humidity":"42.41","iaq":"5.01","id":"14"},{"code":"03e7a84c-46da-4811-a7db-174e79e85c36","createdAt":"2022/7/22 01:37:37","temperature":"29.78","humidity":"41.76","iaq":"0.00","id":"15"},{"code":"ecd81246-5f31-4556-bd68-1f8c4978f2a1","createdAt":"2022/7/22 01:39:24","temperature":"29.81","humidity":"41.62","iaq":"0.00","id":"16"},{"code":"2ccddc1d-1a5d-47a6-8568-e6f424daf90a","createdAt":"2022/7/22 01:41:07","temperature":"29.34","humidity":"42.33","iaq":"4.85","id":"17"},{"code":"03e7a84c-46da-4811-a7db-174e79e85c36","createdAt":"2022/7/22 01:41:42","temperature":"29.88","humidity":"41.60","iaq":"0.00","id":"18"},{"code":"ecd81246-5f31-4556-bd68-1f8c4978f2a1","createdAt":"2022/7/22 01:43:29","temperature":"29.82","humidity":"41.69","iaq":"0.00","id":"19"},{"code":"2ccddc1d-1a5d-47a6-8568-e6f424daf90a","createdAt":"2022/7/22 01:45:12","temperature":"29.36","humidity":"42.38","iaq":"4.96","id":"20"},{"code":"03e7a84c-46da-4811-a7db-174e79e85c36","createdAt":"2022/7/22 01:45:46","temperature":"29.81","humidity":"41.79","iaq":"0.00","id":"21"},{"code":"ecd81246-5f31-4556-bd68-1f8c4978f2a1","createdAt":"2022/7/22 01:47:35","temperature":"29.81","humidity":"41.74","iaq":"0.00","id":"22"}]